invoke_sphinx/__init__.py
invoke_sphinx/docs.py
invoke_sphinx-1.2.0.dist-info/LICENSE
invoke_sphinx-1.2.0.dist-info/METADATA
invoke_sphinx-1.2.0.dist-info/WHEEL
invoke_sphinx-1.2.0.dist-info/top_level.txt
invoke_sphinx-1.2.0.dist-info/RECORD
