Metadata-Version: 2.1
Name: invoke-sphinx
Version: 1.2.0
Summary: Invoke commands related to sphinx documentation
Home-page: https://github.com/Smile-SA/invoke-sphinx
Author: Smile
Author-email: cyrille.gachot@smile.fr
License: UNKNOWN
Platform: UNKNOWN
Classifier: Programming Language :: Python :: 3
Classifier: License :: OSI Approved :: MIT License
Classifier: Operating System :: OS Independent
Requires-Dist: sphinx
Requires-Dist: sphinx-rtd-theme
Requires-Dist: sphinx-autobuild
Requires-Dist: sphinx-versions
Requires-Dist: invoke
Requires-Dist: pyyaml
